README.rst
setup.cfg
setup.py
whapy/Chat.py
whapy/Enums.py
whapy/Message.py
whapy/WhaPy.py
whapy/__init__.py
whapy.egg-info/PKG-INFO
whapy.egg-info/SOURCES.txt
whapy.egg-info/dependency_links.txt
whapy.egg-info/requires.txt
whapy.egg-info/top_level.txt