Metadata-Version: 1.1
Name: whapy
Version: 0.2.0
Summary: A python API for whatsapp web
Home-page: https://github.com/efraimrodrigues/WhaPy
Author: Efraim Rodrigues
Author-email: efraimnaassom@gmail.com
License: MIT
Platform: UNKNOWN
Classifier: Intended Audience :: Developers
Classifier: Natural Language :: English
Classifier: Programming Language :: Python :: 3.4
Classifier: Topic :: Internet
Classifier: Topic :: Software Development :: Libraries
Classifier: Topic :: Software Development :: Libraries :: Python Modules
